cosmoplots/__init__.py
cosmoplots/axes.py
cosmoplots/colors.py
cosmoplots/concat.py
cosmoplots/default.mplstyle
cosmoplots/figure_defs.py
cosmoplots/thick_line.mplstyle
cosmoplots/two_columns.mplstyle
cosmoplots-0.5.0.dist-info/LICENSE
cosmoplots-0.5.0.dist-info/METADATA
cosmoplots-0.5.0.dist-info/WHEEL
cosmoplots-0.5.0.dist-info/RECORD
