Metadata-Version: 2.1
Name: cosmoplots
Version: 0.5.0
Summary: Routines to get a sane default configuration for production quality plots.
Home-page: https://github.com/uit-cosmo/cosmoplots
License: MIT
Author: gregordecristoforo
Author-email: gregor.decristoforo@gmail.com
Requires-Python: >=3.9,<4
Classifier: License :: OSI Approved :: MIT License
Classifier: Programming Language :: Python :: 3
Classifier: Programming Language :: Python :: 3.9
Classifier: Programming Language :: Python :: 3.10
Classifier: Programming Language :: Python :: 3.11
Classifier: Programming Language :: Python :: 3.12
Classifier: Programming Language :: Python :: 3.13
Requires-Dist: importlib-metadata (>=6.6.0,<7.0.0)
Requires-Dist: matplotlib (>=3.3.2)
Requires-Dist: numpy (>=1.15.0)
Requires-Dist: setuptools (>=75.6.0)
